{"MCExpert24":{"issue_post":1},"giovy14":{"issue_post":3},"Alter73":{"issue_post":1},"7hhhhyyyyyu":{"issue_post":1},"coolGi2007":{"pr_post":1,"issue_comment":2},"jillv46":{"issue_post":2},"ALFEECLARE":{"issue_post":1},"villainous-j":{"pr_post":1},"SoumiCN":{"issue_post":1},"eldanielreal":{"issue_post":1,"issue_comment":2},"OMG67":{"issue_post":1},"Heimdallr-1":{"pr_post":1},"REDKING-11":{"issue_post":1},"brch-01":{"issue_post":1,"issue_comment":1},"grisha252":{"issue_post":1},"KahpotVanilla":{"issue_post":1},"Jasmin2277":{"issue_post":1},"wsxiya":{"issue_post":1,"issue_comment":1},"retrixe":{"pr_post":1,"issue_comment":10},"BigManTR1":{"issue_post":1},"FITFC":{"pr_post":1},"Psychodeus":{"issue_post":1,"issue_comment":1},"KIDN0VA":{"issue_post":1},"eagle0idk":{"issue_post":1},"INooBTooMuch":{"issue_post":1,"issue_comment":1},"Whitebrim":{"issue_post":1},"tomlonghorn":{"pr_post":1},"DaDiGui":{"issue_post":1},"Andyghandi":{"issue_post":1,"issue_comment":1},"ItsKondz":{"issue_post":1},"nhmhfv":{"issue_post":1},"Itsironicxx":{"issue_post":2},"Tslat":{"pr_post":2,"issue_comment":3},"NavaEatsSand":{"issue_post":1},"FwuffyPetsOwO":{"issue_post":1},"Cassowarinium":{"issue_post":1},"p3lim":{"issue_post":1},"gmankab":{"issue_post":1},"MarkNoName":{"issue_post":1},"Tobanyi":{"issue_post":1},"ghost":{"issue_post":6,"pr_post":1,"issue_comment":3},"DarkWav":{"pr_post":1},"HeartX94":{"issue_post":1},"NovelQ":{"issue_post":1},"Dr-WeiAL":{"issue_post":1,"issue_comment":1},"Answordy":{"issue_post":1},"vi945786":{"issue_post":1},"mav-8":{"issue_post":1},"AirBeans5956":{"pr_post":1},"RaptaG":{"issue_post":2},"RobertHDPotatoes":{"issue_post":1},"ColdRushYT":{"issue_post":1},"pjdevs":{"issue_post":1,"pr_post":1},"Ecorous":{"issue_post":1},"Zygus42":{"issue_post":1},"tankyap":{"issue_post":1},"itsdinkd":{"issue_post":1,"issue_comment":1},"TurklerRS":{"issue_post":1},"Krampus69":{"issue_post":1},"Boayer":{"issue_post":1},"triphora":{"pr_post":1,"issue_comment":1},"Egitet":{"issue_post":1},"YakaTobori":{"issue_post":1},"IJustWantANamePlease":{"issue_post":1,"issue_comment":3},"unascribed":{"pr_post":1,"issue_comment":1},"squirmby":{"issue_post":1},"Njol":{"pr_post":3,"issue_comment":3},"leon7104":{"issue_post":1,"issue_comment":1},"ApolloTheTwelfth":{"issue_post":1},"lwsx":{"issue_post":1,"issue_comment":1},"Zecka001":{"issue_post":1},"TechPro424":{"issue_post":2},"Nikolass1000":{"issue_post":1,"issue_comment":1},"3D1ofakind":{"issue_post":1},"frodare":{"issue_post":15,"issue_comment":147},"Morgenss":{"issue_post":1,"issue_comment":1},"kkellogg378":{"issue_post":1,"issue_comment":4},"gregCubed":{"issue_post":1,"issue_comment":2},"Shakazu":{"issue_post":1,"issue_comment":1},"Tomatobird8":{"pr_post":2,"issue_comment":1},"zeedif":{"pr_post":1},"xJon":{"issue_post":3,"issue_comment":1},"Arthurmeade12":{"issue_post":1,"issue_comment":1},"ExiledMiner04":{"issue_post":1},"vonrix":{"issue_post":1},"Zienem":{"issue_post":1},"ManWithoutTaste":{"issue_post":1},"jakey1995abc":{"issue_post":2},"ios13-3beta":{"issue_post":1},"MissGamerz":{"issue_post":1},"David-Dude":{"issue_post":1},"ZaneDragonBorn":{"issue_post":1,"issue_comment":1},"DereC4":{"issue_post":1},"CTAK-CO6AK":{"pr_post":4,"issue_post":1,"issue_comment":6},"Asuryan2001":{"issue_post":1,"issue_comment":1},"supsm":{"issue_post":2},"K0-RR":{"issue_post":1,"issue_comment":1},"FatalCreations":{"issue_post":1},"Forturian":{"issue_post":1},"FewerFlaws":{"issue_post":1,"issue_comment":4},"MeeniMc":{"issue_post":3,"issue_comment":2},"Blobanium":{"issue_post":1},"Nazguliki":{"issue_post":1},"TheRealZonko":{"issue_post":1},"PlNG":{"issue_post":1},"NielsPilgaard":{"issue_post":2,"issue_comment":2},"Taknax":{"issue_post":1},"kihgy":{"issue_post":1},"Coraline77447":{"issue_post":1},"xdjzack":{"issue_post":1},"IdrisQe":{"issue_post":1},"VL4DST3R":{"issue_post":1},"Waesh":{"issue_post":1},"Golemgator":{"issue_post":1,"pr_post":1},"Joseph101GH":{"issue_post":1},"PiggiesGoSqueal":{"issue_post":1},"Bulldog83":{"pr_post":3,"issue_comment":4},"abouteiller":{"issue_post":1,"issue_comment":1},"ShinoAsada":{"issue_post":1,"issue_comment":1},"UndarkAido":{"issue_post":1},"alpinek2008":{"issue_post":1},"Yourname942":{"issue_post":1,"issue_comment":1},"thegamerx1":{"issue_post":1},"firyy":{"issue_post":1,"issue_comment":1},"TRRESTGHGYTCFTGBCXSZD":{"issue_post":1,"issue_comment":1},"awesomeayaan13":{"issue_post":1},"Xiaminou":{"issue_post":1},"Boolyman":{"issue_post":1,"issue_comment":1},"Drehverschluss":{"issue_post":1,"issue_comment":1},"zeriley":{"issue_post":10,"issue_comment":10},"conc1erge":{"issue_post":1,"issue_comment":1},"Kylebartaous":{"issue_post":1,"issue_comment":1},"AGSPhoenix":{"pr_post":1},"LlubNek":{"issue_post":1},"kreezxil":{"issue_post":1},"ssamjh":{"issue_post":1},"LemADEC":{"issue_post":1,"issue_comment":1},"PPKOOL":{"issue_post":1},"PCGaming247":{"issue_comment":2},"judgekreep":{"issue_comment":1},"vin0m":{"issue_comment":1},"JayZX535":{"issue_comment":1},"MelnCat":{"issue_comment":1},"Motschen":{"issue_comment":2},"ajloveslily14":{"issue_comment":1},"Acrivec":{"issue_comment":2},"DoltenBolten":{"issue_comment":1},"NEOLEE98":{"issue_comment":3},"MarinaMarissa":{"issue_comment":1},"GeradesoLukas":{"issue_comment":1},"Naheulf":{"issue_comment":1},"PTA00":{"issue_comment":1},"TheIrishLadYT":{"issue_comment":2},"n0itLT":{"issue_comment":1},"MattB70":{"issue_comment":1},"LightHardt":{"issue_comment":1},"DisasterInbound":{"issue_comment":1},"J053Fabi0":{"issue_comment":2},"megabyte6":{"issue_comment":1},"Sparkzzzzzz":{"issue_comment":2},"PRRB":{"issue_comment":1},"papertek":{"issue_comment":1},"brunociria":{"issue_comment":1},"CuboidRaptor":{"issue_comment":1},"Annijang":{"issue_comment":2},"sandornot":{"issue_comment":1},"Figgmastah":{"issue_comment":2},"HowardZHY":{"issue_comment":2},"fijidarko":{"issue_comment":1},"Kxsumi":{"issue_comment":1},"mbassie":{"issue_comment":1},"Gamemassa":{"issue_comment":1},"ZsoltMolnarrr":{"issue_comment":2},"MC-Gary003":{"issue_comment":2},"gitguette":{"issue_comment":1},"Sakurokamizenakura":{"issue_comment":1},"lxly9":{"issue_comment":1},"MrOz59":{"issue_comment":2},"qguo-gid":{"issue_comment":1}}