{"BioTechproject27":{"issue_post":1},"MOS12546":{"issue_post":1,"issue_comment":1},"robotter112":{"issue_post":1,"issue_comment":1},"CsiPA0723":{"issue_post":1},"lukenator115":{"issue_post":1},"meglazero":{"issue_post":1},"19-creator":{"issue_post":1,"issue_comment":1},"Liva-G":{"pr_post":1},"Poopooracoocoo":{"issue_post":2},"Heimdallr-1":{"pr_post":1,"pr_comment":1},"GundamDr1ver":{"issue_post":1},"Diemoerm":{"issue_post":1},"Velken":{"issue_post":1},"Coraline774477":{"issue_post":1,"issue_comment":1},"800020h":{"issue_post":1},"Sorro123":{"issue_post":1},"Zerobine":{"issue_post":1},"coco875":{"issue_post":1,"issue_comment":1},"Gordon-Frohman":{"issue_post":1},"FITFC":{"pr_post":1},"peacegangsta":{"issue_post":1},"finalsecure":{"issue_post":1},"FoxTriforce":{"issue_post":1,"issue_comment":3},"Matt008X":{"issue_post":1},"mixiymixinout":{"issue_post":1,"issue_comment":2},"f-denis":{"issue_post":1,"issue_comment":1},"v1-valux":{"issue_post":1},"BrianPetkovsek":{"pr_post":1},"PermskyKit":{"issue_post":1},"MiniRaptor":{"pr_post":1,"issue_post":1},"HonzaVinCZ":{"pr_post":1},"p1ut0nium-git":{"issue_post":2},"mindy15963":{"pr_post":1},"FenixTheXD":{"issue_post":1},"mosharky":{"issue_post":1},"Kleptobismaniac":{"issue_post":1,"issue_comment":1},"GabrielToth":{"issue_post":1},"HopsandBarley":{"issue_post":1,"issue_comment":1},"zndrmn":{"issue_post":1,"issue_comment":1},"KhanhPham05":{"issue_post":1},"juraj-hrivnak":{"issue_post":2,"issue_comment":1},"ChloeDawn":{"issue_post":12,"issue_comment":4},"IronlegacyXVII":{"issue_post":1},"sfiomn":{"issue_post":1,"issue_comment":1},"EliotWL":{"issue_post":1},"TomaszBarowiec":{"issue_post":1},"Autismacus":{"issue_post":1},"luxlacis":{"issue_post":2,"issue_comment":2},"wcdanh2":{"issue_post":1},"ZekerZhayard":{"issue_post":1,"issue_comment":1},"HoneyGears":{"issue_post":1},"Alexiserist":{"issue_post":1,"issue_comment":1},"Adamiyevsty":{"issue_post":1},"kuroyure":{"issue_post":1},"Shandoo94":{"issue_post":1,"issue_comment":2},"SouthernPixel":{"issue_post":1,"issue_comment":1},"No3371":{"issue_post":2,"issue_comment":3},"Coraline77447":{"issue_post":1},"BugmanBugman":{"issue_post":2,"issue_comment":4},"jackg2527":{"issue_post":1},"Oethever":{"issue_post":1,"issue_comment":1},"Hisoka098":{"issue_post":1},"Geezt435":{"issue_post":5,"issue_comment":3},"wenseul":{"issue_post":1},"yezhiyi9670":{"issue_post":1},"Powerless001":{"issue_post":1},"Wgairborne":{"issue_post":1,"issue_comment":1},"vicitafirea":{"issue_post":1,"issue_comment":5},"minerchy":{"issue_post":2,"issue_comment":1},"Sageking10":{"issue_post":1},"Terrahop":{"issue_post":1},"floral-qua-floral":{"issue_post":2},"RodrigoTaipe93":{"issue_post":2},"DemonfangArun":{"issue_post":1},"Zack7292":{"issue_post":1,"issue_comment":1},"thegamerx1":{"issue_post":1},"BedrockLegends":{"issue_post":1},"Charles445":{"issue_post":1,"issue_comment":1},"sepsol":{"issue_post":1},"mxnmnm":{"issue_post":2,"issue_comment":8},"Parthurax":{"issue_post":1,"issue_comment":3},"kellixon":{"issue_post":1},"rlnt":{"issue_post":1},"Spiderfoxtail":{"issue_post":1,"issue_comment":2},"Nick-77ab2":{"issue_post":1,"issue_comment":6},"VirtualGaming1":{"issue_post":2,"issue_comment":17},"EndangeredNayla":{"issue_post":1,"issue_comment":1},"Martmists-GH":{"issue_post":1,"issue_comment":2},"lofcz":{"issue_post":1},"KenyMylankca":{"issue_post":1,"issue_comment":1},"shoverno2":{"issue_post":1},"ScienceDrummer":{"issue_post":1,"issue_comment":1},"Avery93":{"issue_post":1},"rosenclosed":{"issue_post":1,"issue_comment":1},"cosmicdan":{"issue_post":1,"issue_comment":1},"000THEALPHA000":{"issue_post":1,"issue_comment":1},"DR01D-Qs":{"issue_post":1},"zach2045":{"issue_post":1,"issue_comment":1},"NolanSyKinsley":{"issue_post":1},"O13SC3N3":{"issue_post":1,"issue_comment":2},"Bvioto":{"issue_post":1},"SirHaxe":{"issue_post":1},"Snownee":{"issue_post":3,"issue_comment":3},"corgiblu":{"issue_post":2},"duhnunes":{"issue_post":1},"wenlfs":{"issue_post":2,"issue_comment":1},"Trinsdar":{"issue_post":1},"TheRealDadbeard":{"issue_post":2,"issue_comment":4},"garoninja":{"issue_post":1},"Tereo725":{"issue_post":1},"NovaViper":{"issue_post":2,"issue_comment":1},"Efimero":{"issue_post":1},"Fireztonez":{"issue_post":1,"issue_comment":2},"brisingraerowing":{"issue_post":1},"Cazadorsniper":{"issue_post":3},"L-Clouds":{"issue_post":1,"issue_comment":1},"XBagon":{"issue_post":1,"issue_comment":1},"ghost":{"issue_post":10,"issue_comment":30},"Sonic2423":{"issue_post":1},"VoilaTada":{"issue_post":1,"issue_comment":2},"MooCowGal":{"issue_post":1},"thephoenixlodge":{"issue_post":1},"Claycorp":{"issue_post":1,"issue_comment":1},"Lightone":{"issue_post":2,"issue_comment":4},"DBotThePony":{"issue_post":1},"Drakoflame":{"issue_post":1,"issue_comment":1},"Zarepheth":{"issue_post":1,"issue_comment":1},"Sir-Will":{"issue_post":1,"issue_comment":1},"Bushcrafts":{"issue_post":1},"InsaneJ":{"issue_post":1},"CreativeMD":{"issue_post":1,"issue_comment":296,"pr_comment":3},"Troock":{"issue_post":1,"issue_comment":2},"GamerForYears":{"issue_post":1,"issue_comment":3},"Svedrigailov":{"issue_post":1},"MattSkar":{"issue_post":1},"plaguewolf":{"issue_post":1,"issue_comment":1},"Labna":{"issue_post":1},"thegoldtrain342":{"issue_post":1,"issue_comment":1},"Sebbed04":{"issue_post":1,"issue_comment":22},"DeathRtH":{"issue_post":1},"kreezxil":{"issue_post":1},"WizardZartak":{"issue_post":1,"issue_comment":1},"MissPotato":{"issue_post":1,"issue_comment":1},"Blewm":{"issue_post":1,"issue_comment":1},"joshmoni":{"issue_post":1,"issue_comment":1},"BobHassok":{"issue_post":1,"issue_comment":2},"mdfiot":{"issue_post":1,"issue_comment":1},"lrac1998":{"issue_post":1},"Benjomaster":{"issue_post":1,"issue_comment":1},"jakimfett":{"issue_comment":1},"ryantheleach":{"issue_comment":1},"gabizou":{"issue_comment":4},"Mysteryem":{"issue_comment":2},"CDAGaming":{"issue_comment":3},"percivalalb":{"issue_comment":1},"SeanChengN":{"issue_comment":1},"mmmilord":{"issue_comment":3},"stonemandave":{"issue_comment":2},"Dimitry-Blitzbrieg":{"issue_comment":2},"Leejit":{"issue_comment":1},"MrCrayfish":{"issue_comment":1},"Wolfstar1010":{"issue_comment":1},"zDragoNzz":{"issue_comment":2},"zachs18":{"issue_comment":1},"amoooooo":{"issue_comment":1}}