{"Raycoms":{"pr_post":86,"issue_post":6,"issue_comment":238,"pr_comment":127},"Jinotad":{"issue_post":4,"issue_comment":3},"Moobien":{"issue_post":7,"issue_comment":11,"pr_comment":1},"Nightenom":{"issue_post":21,"pr_post":60,"issue_comment":195,"pr_comment":80},"ExileWind":{"issue_post":1,"issue_comment":1},"someaddons":{"pr_post":25,"issue_post":1,"issue_comment":31,"pr_comment":11},"Howman":{"issue_post":3,"issue_comment":3},"kezmodius":{"issue_post":1},"uecasm":{"pr_post":54,"issue_post":2,"issue_comment":32,"pr_comment":75},"LinkTheLinker":{"issue_post":1},"kwerin":{"issue_post":1},"hellwolf95":{"issue_post":1},"AndyClausen":{"issue_post":1},"Shadizar":{"issue_post":2,"issue_comment":9},"thepriz":{"issue_post":2,"issue_comment":3},"Sandriell":{"issue_post":5,"pr_post":1,"pr_comment":1,"issue_comment":1},"P3rf3ctXZer0":{"issue_post":3,"issue_comment":3},"MediaFoxxx":{"issue_post":1,"issue_comment":2},"FatesTimelines1337":{"issue_post":1,"issue_comment":1},"fujcycle13":{"issue_post":1,"issue_comment":2},"drakray":{"issue_post":1},"Xirnbruaddict":{"issue_post":1},"flyingfoxjames":{"issue_post":1},"Thodor12":{"pr_post":4,"issue_post":2,"issue_comment":5,"pr_comment":5},"DSMister":{"issue_post":1},"deVDem":{"issue_post":1,"issue_comment":4},"Mekle001":{"pr_post":1,"pr_comment":1},"Nyagguar":{"issue_post":1,"issue_comment":1},"Psychoren":{"issue_post":1,"issue_comment":2},"v-lkyrie":{"issue_post":1,"issue_comment":2},"JerryTC1":{"issue_post":1},"Vritra22189":{"issue_post":1},"DraftySea1997":{"issue_post":1,"issue_comment":1},"YogoGeeButch":{"issue_post":1},"SignalEquation":{"issue_post":1,"issue_comment":1},"anonymous563":{"issue_post":1},"TheCommensuratePup":{"issue_post":1,"issue_comment":2},"cclee1103":{"issue_post":1},"emanuele246gi":{"issue_post":1,"issue_comment":2},"Ilomaros":{"issue_post":1},"jjjjj8797":{"issue_post":1,"issue_comment":1},"PurpleHel":{"issue_post":1,"issue_comment":1},"FITFC":{"issue_post":2},"Veylyn":{"issue_post":1,"issue_comment":1},"EliotWL":{"issue_post":3,"issue_comment":2},"Spumantii":{"issue_post":1,"issue_comment":7},"wuggyfoot":{"issue_post":1},"ethansyy":{"issue_post":1},"TheaRTGGaming":{"issue_post":1,"issue_comment":4},"HeraMain":{"issue_post":1},"Taknax":{"issue_post":1},"Zano1999":{"issue_post":1},"adam110902":{"issue_post":1},"Swantsy":{"issue_post":2,"issue_comment":1},"DefaultUSERNAME9":{"issue_post":1},"SivartMcDorf":{"issue_post":3,"issue_comment":8},"Yesssssman":{"issue_post":1},"niftybottle":{"issue_post":1,"issue_comment":1},"Nikademus":{"issue_post":1},"jackplackjack":{"issue_post":1,"issue_comment":2},"MarkusBordihn":{"pr_post":1,"issue_post":1,"issue_comment":1},"lebanni":{"issue_post":3,"issue_comment":4},"DarQuing":{"issue_post":1},"Grimmspecter":{"issue_post":1,"issue_comment":2},"Derjinjon":{"issue_post":1,"issue_comment":2},"Z4X4R0FF":{"issue_post":1,"issue_comment":1},"ghost":{"issue_post":3,"issue_comment":5},"TheRooster13":{"issue_post":1,"issue_comment":5},"e30Birdy":{"issue_post":1},"drago87":{"issue_post":1},"Maurony17":{"issue_post":1},"SaintWacko":{"issue_post":1},"Talyda":{"issue_post":1,"issue_comment":23,"pr_comment":1},"MotionlessTrain":{"issue_post":1,"pr_post":1,"pr_comment":2,"issue_comment":17},"PhoenixRiver":{"issue_post":1},"Farfi8":{"issue_post":1},"ChaoChild":{"issue_post":1,"issue_comment":1},"FaeTech":{"issue_post":1},"CosmicGlowsticks":{"issue_post":1,"issue_comment":1},"TagnumElite":{"pr_post":1,"pr_comment":2},"warning-djkajslh":{"issue_post":4,"issue_comment":1},"Lester702":{"issue_post":1,"issue_comment":3},"ravenbuilder934":{"pr_post":21,"issue_post":3,"issue_comment":63,"pr_comment":20},"Mr-Syntax":{"issue_post":1,"issue_comment":1},"Shaxcur":{"issue_post":1},"VENNTennison":{"issue_post":1},"codec-d":{"issue_post":1,"issue_comment":2},"IchHabeHunger54":{"issue_post":1},"leagris":{"issue_post":1,"pr_post":1,"pr_comment":1,"issue_comment":2},"tim20010803":{"issue_post":1},"AngleWyrm10":{"issue_post":1},"WenXin20":{"issue_post":5,"pr_post":2,"issue_comment":4,"pr_comment":2},"TokyOnch":{"issue_post":1},"Justen-N":{"pr_post":2,"pr_comment":6,"issue_comment":2},"BigEyesOMG":{"issue_post":1},"IchigoGames":{"issue_post":1},"FesterHead":{"issue_post":1},"Nooska":{"issue_post":1},"Kriiks":{"issue_post":1,"issue_comment":1},"LegendaryGeek":{"issue_post":1},"AlmightyChan":{"issue_post":1},"ShadowProtocol":{"pr_post":16,"issue_comment":2,"pr_comment":17},"dhouck":{"issue_post":4,"issue_comment":5},"starfall18":{"issue_post":1,"issue_comment":3},"dupontct":{"issue_post":4,"issue_comment":5},"Skyibis":{"issue_post":1,"issue_comment":1},"Electrocutor":{"issue_post":1,"issue_comment":2},"gattsuru":{"pr_post":3,"pr_comment":1},"Haelis":{"issue_post":1,"issue_comment":3},"kihgy":{"issue_post":2,"issue_comment":5},"DestroyEarthlings":{"issue_post":1,"issue_comment":1},"insufficient-funds":{"issue_post":1,"issue_comment":1},"ederlezi29":{"issue_post":2,"issue_comment":2},"Hruvitnir":{"issue_post":1},"sausagemadness":{"issue_post":1},"flippyer":{"issue_post":1},"SiliconAshes":{"issue_post":1,"issue_comment":3},"docduke1":{"issue_post":1,"issue_comment":2},"SharkWipf":{"issue_post":1,"issue_comment":2},"Mechrior":{"issue_post":1,"issue_comment":2},"kedamono":{"issue_post":3,"issue_comment":3},"SteadEXE":{"issue_post":1},"ARamlall":{"issue_post":1,"issue_comment":1},"AnthonyHeide":{"issue_post":1,"issue_comment":2},"Coraline77447":{"issue_post":1,"issue_comment":3},"marchermans":{"pr_post":9,"issue_comment":43,"pr_comment":21},"TechyShishy":{"pr_post":1,"issue_post":1,"issue_comment":2,"pr_comment":1},"anakhasilver":{"issue_post":1},"groverfield":{"issue_post":1},"Ethankim12":{"issue_post":1,"issue_comment":6},"TheLewtz":{"issue_post":1},"snipechan":{"issue_post":1,"issue_comment":2},"Orinai":{"issue_post":1},"thaylar":{"issue_post":4,"issue_comment":1},"rustyred41":{"issue_post":1},"Donut7163":{"issue_post":1},"oddrobbia":{"issue_post":1,"issue_comment":4},"AndrewTru":{"issue_post":1,"issue_comment":4},"firestorm2039":{"issue_post":1},"Hellfire1317":{"issue_post":1},"Ampaex":{"issue_post":1,"issue_comment":1},"Edison12300":{"issue_post":1},"ErikderFreak":{"issue_post":1},"pirateorion":{"issue_post":1},"Camreyn":{"issue_post":1,"issue_comment":2},"FearAK":{"issue_post":1,"issue_comment":2},"LordMeta":{"issue_post":1},"Moleculor":{"issue_post":1},"othuntgithub":{"pr_post":1},"BabBimmaBome":{"issue_post":1,"issue_comment":1},"CodyMW":{"issue_post":2,"issue_comment":1},"Lejoni":{"issue_post":1},"Sanysvo":{"issue_post":1,"issue_comment":1},"Fodoth-jinzi89":{"pr_post":1,"pr_comment":1},"Gimmie053":{"issue_post":1},"sciwhiz12":{"pr_post":1},"77Florian99":{"issue_post":1,"issue_comment":2},"SylviaFox":{"issue_post":1,"issue_comment":2},"pugsarepeople2":{"issue_post":3},"mvdhoning":{"issue_post":1},"Darkhax":{"pr_post":1},"TheOrionsun":{"issue_post":1},"WarpedFoxx":{"issue_post":1},"AkGamerRo":{"issue_post":1},"JayGame45":{"issue_post":1},"Bryntet":{"issue_post":1,"issue_comment":4},"juliashepp":{"issue_post":1,"issue_comment":1},"boneskull":{"issue_post":1,"issue_comment":10},"suduko666":{"issue_post":1,"issue_comment":4},"perecnicek":{"issue_post":1,"issue_comment":4},"ProfMidnightX":{"issue_post":1},"LuckyFalkor":{"issue_post":2,"issue_comment":1},"loudwhitenoise":{"issue_post":1},"PowerSchill":{"issue_post":2,"pr_post":5,"issue_comment":11,"pr_comment":1},"budgej":{"issue_post":1,"issue_comment":1},"Kojoley":{"pr_post":1,"pr_comment":2},"Dragolance117":{"issue_post":1,"issue_comment":1},"ClaudiusMinimus":{"issue_post":1,"issue_comment":1},"Snoopydude":{"issue_post":1},"ANAND388":{"pr_post":1},"DouglasHennrich":{"issue_post":1},"cinnamennen":{"issue_post":1,"issue_comment":1},"Nachtflame":{"issue_post":1},"elijahalemard":{"issue_post":1},"ocram9":{"issue_post":1},"Pythonic-Rainbow":{"issue_post":1,"issue_comment":5},"CHead2000":{"issue_post":1,"issue_comment":1},"OuroborosBoy":{"issue_post":1},"lunadragnstar":{"issue_post":4,"issue_comment":4},"yyttuuyy":{"issue_post":1},"Gaiboru":{"issue_post":1},"Strohtaler":{"issue_post":2,"issue_comment":5},"Baaliazaar":{"issue_post":1},"Tricksta1999":{"issue_post":1},"trzebiaf":{"issue_post":2,"issue_comment":1},"jolesh":{"issue_post":1,"issue_comment":1},"RyuuSlayer":{"issue_post":1,"issue_comment":2},"mcmanustfj":{"pr_post":1},"DiabolosMan":{"issue_post":1,"issue_comment":1},"Residentj3553":{"issue_post":1,"issue_comment":1},"ToMe25":{"pr_post":1,"pr_comment":2,"issue_comment":5},"Asherslab":{"pr_post":8,"issue_post":2,"pr_comment":11,"issue_comment":16},"LearnerZ":{"issue_post":1},"norfair00":{"issue_post":1},"iiEpic":{"issue_post":1},"theoklm":{"issue_post":1},"NiickNICHEN":{"issue_post":1},"RolanDecoy":{"issue_post":1},"jrjespersen":{"issue_post":1,"issue_comment":1},"Kosmic138":{"pr_post":1,"pr_comment":1},"T-Grave":{"issue_post":1,"issue_comment":10},"calpluca":{"issue_post":1,"issue_comment":2},"Gisssmo":{"issue_post":1},"MatthiasMann":{"issue_post":1},"Trampler60":{"issue_post":1,"issue_comment":1},"EnterFor":{"pr_post":1},"colhampt":{"issue_post":1},"lordSeaworth":{"issue_post":1},"kreezxil":{"issue_post":1,"issue_comment":4},"Matthysse":{"issue_post":1},"tiphilou17":{"issue_post":1,"issue_comment":2},"gswvmware":{"pr_post":2},"April25th-mc":{"issue_post":1,"issue_comment":1},"RyTechro":{"pr_post":1,"pr_comment":1},"Elrol":{"issue_post":1},"pandory-network":{"issue_post":1},"RuneVanguard":{"issue_post":1,"issue_comment":15},"Bucketsmith":{"issue_post":2,"issue_comment":5},"nephatrine":{"issue_post":1},"Bunker-Kenyon":{"issue_post":1,"issue_comment":3},"Kaspertje":{"issue_post":1,"issue_comment":1},"cdc1671":{"issue_post":1},"ProsperCraft":{"issue_post":5,"issue_comment":4},"kellixon":{"issue_post":1,"pr_post":1},"dependabot-preview[bot]":{"pr_post":10,"pr_comment":10},"DoggoBoi":{"issue_post":1,"issue_comment":1},"GanthorPrime":{"issue_post":1,"issue_comment":1},"sm9cc":{"issue_post":1,"issue_comment":2},"barthogenes":{"pr_post":1},"ipradasgomez":{"issue_post":1,"issue_comment":1},"Rumpelstiltskinny":{"issue_post":1,"issue_comment":3},"JTK222":{"pr_post":2},"Wissi":{"issue_post":1,"issue_comment":1},"spacewolfcub":{"issue_post":1},"LemADEC":{"issue_post":1},"sharkck":{"issue_post":1,"issue_comment":3},"CharCharthemonkey":{"issue_post":1,"issue_comment":3},"PoroUsedSnax":{"issue_comment":1},"cltnschlosser":{"pr_comment":1},"CLAassistant":{"pr_comment":31},"darthvader45":{"issue_comment":3},"stormbringerGT":{"issue_comment":1},"Dracos99":{"issue_comment":1},"Sharkykzn":{"issue_comment":1},"Megistus":{"issue_comment":7},"cathaldus2":{"issue_comment":2},"ZsomborRajki":{"issue_comment":3},"holty07":{"issue_comment":3},"lucsoft":{"issue_comment":16},"TaylorMaker54":{"issue_comment":3},"Gerflargle":{"issue_comment":1},"Dokharus":{"issue_comment":1},"malte0811":{"pr_comment":3},"FrannDzs":{"issue_comment":3},"smmmadden":{"issue_comment":3},"robbinsmitje":{"issue_comment":1},"DaddyP1G":{"issue_comment":1},"sandalle":{"issue_comment":1},"Rice-SD":{"issue_comment":2},"CraftSpider":{"issue_comment":1},"Zorgatone":{"issue_comment":1},"VirtualZer0":{"issue_comment":2},"ZRunner":{"issue_comment":1},"imanairconditioner":{"issue_comment":1},"NicksCraft2007":{"issue_comment":5},"EnderKidRs":{"issue_comment":1},"QUEWEX":{"issue_comment":1},"Pablo-DS":{"issue_comment":2},"ansaruman":{"issue_comment":3},"Pancake010":{"issue_comment":1},"Nullzee":{"issue_comment":1},"Sovreighn":{"issue_comment":1},"rrusciguy":{"issue_comment":1},"bakuscout":{"issue_comment":1}}