{"gitdrug":{"issue_post":1},"renovate[bot]":{"pr_post":1,"pr_comment":1},"Osimarus":{"pr_post":2},"dandin87":{"issue_post":1},"Felix14-v2":{"pr_post":2,"issue_post":1,"pr_comment":1,"issue_comment":1},"RooftopJoe":{"pr_post":3,"pr_comment":2,"issue_comment":1},"LeoK77S":{"issue_post":1},"ghost":{"issue_post":1,"issue_comment":1},"Boobies":{"issue_post":1,"issue_comment":2},"egeesin":{"pr_post":2},"haykam821":{"issue_post":1},"Romz24":{"pr_post":1,"pr_comment":1},"BlueSkyClouds":{"pr_post":1},"florensie":{"pr_comment":7,"issue_comment":6},"zax71":{"issue_comment":1}}