{"cerealconjugo":{"pr_post":2},"fivelol":{"issue_post":13,"issue_comment":7},"unroman":{"pr_post":4},"gyrozeppelifan":{"pr_post":1},"LaGz4643":{"issue_post":5,"issue_comment":2},"SlayDigger":{"issue_post":1},"OrithanFox":{"issue_post":1,"issue_comment":1},"neverdestroyer23":{"pr_post":1,"issue_comment":1,"pr_comment":1},"CelestaGlacier":{"issue_post":1},"nbdeity":{"issue_post":1},"SerJoG":{"issue_post":1},"Aceplante2":{"issue_post":1,"issue_comment":1},"BlazinAmazin":{"issue_post":1},"gisellevonbingen":{"pr_post":1},"thelegitdolt":{"issue_post":13,"pr_post":2,"issue_comment":14},"cylyme":{"issue_post":1},"Numerosityy":{"issue_post":1},"Reshy":{"issue_post":2},"Tomat777":{"issue_post":1},"1mtwtfss1":{"issue_post":1,"issue_comment":1},"HuanMeng-official":{"issue_post":1},"Erxti":{"issue_post":1},"Poulpster":{"pr_post":1},"TheMagicalSC":{"issue_post":1},"sigmastar00":{"issue_post":1,"issue_comment":1},"MarshmallowFloof":{"issue_post":1},"AdalynBlack":{"issue_post":1,"issue_comment":1},"CraftyG":{"issue_post":1,"issue_comment":1},"Telezhka-the-First":{"pr_post":1},"saltyseadoggo":{"issue_post":2},"jogurciQ":{"issue_post":1,"pr_post":1},"ghost":{"pr_post":4,"issue_post":1},"doubleaxes":{"issue_post":1},"WitheredWasabi":{"issue_post":12,"issue_comment":2},"Kulkowaty":{"issue_post":1},"TheDeviantCrafter":{"issue_post":2},"RaymondBlaze":{"issue_post":1},"juebster":{"issue_post":1},"shrooompy":{"issue_post":1},"skydexx18":{"issue_post":1},"GangstaPichu":{"issue_post":1},"PssbleTrngle":{"pr_post":2,"issue_post":1},"ExDrill":{"issue_post":1},"baooduy":{"pr_post":1},"MrFastZombie":{"issue_post":1},"Soul-Rack":{"issue_post":1},"LLavender-Az":{"issue_post":1},"MasterIMLG":{"issue_post":1},"arcticgalaxies":{"issue_post":1},"Zygus42":{"issue_post":1},"GatoLeyo":{"issue_post":1,"issue_comment":1},"Bonniethebunny-hub":{"pr_post":1},"AzureDoom":{"issue_post":1},"kuddyh3ct0r":{"issue_post":2,"issue_comment":2},"jlaine3333":{"issue_post":1},"birdyalo":{"issue_post":1},"LobaaChe":{"pr_post":1},"IwasConfused":{"pr_post":1},"tarinoita":{"pr_post":1,"pr_comment":1},"Snorps":{"issue_post":1,"issue_comment":1},"HyDefier":{"issue_post":1},"felinux02":{"pr_post":15},"SimGitHub5":{"pr_post":1},"VerdaPegasus":{"pr_post":1},"Carmenboy1":{"issue_post":1},"GauntAndreX8":{"issue_post":1},"MarioSMB":{"issue_post":6,"issue_comment":4},"HJ-zhtw":{"pr_post":1},"GDmitch":{"issue_post":1,"issue_comment":1},"therealfunnelton":{"issue_post":1},"flowerfugue":{"pr_post":1},"Brun333rp":{"pr_post":3,"issue_post":1,"issue_comment":2,"pr_comment":2},"Nekkok":{"issue_post":1},"sapphicgoddessorwhatever":{"issue_post":3,"issue_comment":1},"Not-February":{"issue_post":1,"issue_comment":1},"pm065":{"issue_post":1},"AdeptusAutumn":{"issue_post":1},"trepidotractatos":{"issue_post":2},"laserlemons":{"issue_post":1},"Smokedeuch":{"issue_post":1},"Quaerere-Git":{"pr_post":4},"EltrutLikes":{"pr_post":5},"Kagaribi172":{"pr_post":1},"CheetahCyberBoi":{"issue_post":1,"issue_comment":2},"idodana":{"pr_post":1},"DarianLStephens":{"issue_post":1},"Rozarke":{"issue_post":1},"rafaelkai":{"issue_post":1,"issue_comment":1},"SirChamomile":{"issue_post":1,"issue_comment":1},"Vaelzan":{"issue_post":1,"issue_comment":1},"CyberNewty":{"issue_post":1},"ChloeDawn":{"pr_post":1},"Vazkii":{"pr_post":1,"issue_post":1},"othuntgithub":{"pr_post":2},"WuzgXY-GitHub":{"pr_post":2},"QuiteABit":{"issue_post":1},"zsn741656478":{"issue_post":1},"BardinTheDwarf":{"pr_post":1},"davidjjung":{"issue_post":1,"issue_comment":1},"SatDog92":{"issue_post":1},"bageldotjpg":{"issue_post":1,"issue_comment":66,"pr_comment":6},"Moofellow":{"issue_post":1},"BrauneDe":{"pr_post":1},"Estellarium":{"pr_post":3},"Greymanz":{"issue_post":1},"Markus1002":{"pr_post":1,"issue_comment":1},"nrtcb":{"issue_post":1},"Ad3lineL":{"issue_comment":1},"SeriousCreeper":{"issue_comment":1},"Pannoniae":{"issue_comment":1},"ShockMicro":{"issue_comment":1},"Jarlenai":{"issue_comment":1},"Raithion":{"issue_comment":1},"Lgmrszd":{"issue_comment":1},"SuggestionMan":{"issue_comment":1},"HanatakeYurii":{"issue_comment":3},"DarkeFae":{"issue_comment":1}}