{"johancilliers22":{"pr_post":1,"pr_comment":1},"Supbrosky1":{"issue_post":1,"issue_comment":1},"serioos":{"issue_post":1,"issue_comment":4},"xFirefalconx":{"issue_post":1},"ChromaPIE":{"issue_post":2},"ildiem":{"issue_post":1,"issue_comment":1},"viktordimov":{"issue_post":1,"issue_comment":4},"kualatoni":{"issue_post":2,"issue_comment":1},"TheWitherlord":{"issue_post":1,"issue_comment":2},"ShayBox":{"issue_post":1,"issue_comment":1},"Guzza46":{"issue_post":1,"issue_comment":5},"ZerJ704":{"issue_post":1,"issue_comment":2},"Defflix":{"issue_post":1},"kittech0":{"issue_post":1},"apostrophepi":{"issue_post":1,"issue_comment":1},"GigaNybl":{"issue_post":1},"CoderXL1":{"issue_post":1},"Hexblood":{"issue_post":1},"LenKagamine":{"issue_post":1},"some-du6e":{"issue_post":2},"630R63":{"issue_post":1,"issue_comment":1},"Flexz9":{"issue_post":1,"issue_comment":3},"ImASadBoy":{"issue_post":1},"c0gd1s":{"issue_post":1,"issue_comment":3},"stunlocked1":{"issue_post":1},"Fuzss":{"issue_post":1,"issue_comment":144,"pr_comment":1},"mpustovoi":{"issue_post":1,"issue_comment":1},"CherriCola":{"issue_post":1},"cobaltlol":{"issue_post":1,"issue_comment":4},"Steveplays28":{"issue_post":1,"issue_comment":2},"natkos21":{"issue_post":1,"issue_comment":2},"BITS-US":{"issue_post":1,"issue_comment":1},"NoIDidntHackU":{"issue_post":1,"issue_comment":1},"mxKeaton":{"issue_post":1},"DSLZL":{"issue_post":1},"aanthonyssandoval1999":{"issue_post":1,"issue_comment":6},"Afrocntrik":{"issue_post":1},"NICKOLAS78GR":{"issue_post":1},"Neubulae":{"issue_post":1,"issue_comment":2},"GentlemanCheesy":{"issue_post":1},"rainysux":{"issue_post":1},"wolfie0112":{"issue_post":1,"issue_comment":3},"timingplanet":{"issue_post":1,"issue_comment":4},"Moosheking":{"issue_post":1,"issue_comment":1},"dalekfan":{"issue_post":1,"issue_comment":1},"Two-pixel":{"issue_post":1},"Lieliel":{"issue_post":1,"issue_comment":1},"Rozbiynk":{"issue_post":1},"vico93":{"issue_post":1},"PaynMusic":{"issue_post":1},"Jusey1":{"issue_post":1},"FAKHORII":{"issue_post":1,"issue_comment":2},"Tarazzo":{"issue_post":1},"drakosoldier298":{"issue_post":1,"issue_comment":2},"noiverre":{"issue_post":1},"suerion":{"issue_post":1,"issue_comment":2},"cyrusconan402":{"issue_post":1},"axieum":{"issue_post":1},"Na7uralone1":{"issue_post":1},"embeddedt":{"issue_post":1,"issue_comment":1},"Cape-City":{"issue_post":2,"issue_comment":2},"VsUK":{"issue_post":1},"Minebrah":{"issue_post":1},"Alec153":{"issue_post":1},"Arkadyaaa":{"issue_post":1},"rapus95":{"issue_post":1,"issue_comment":1},"WFPhantom":{"issue_post":1},"zSoulweaver":{"issue_post":1},"Rogenar":{"issue_post":1,"issue_comment":1},"harithmf":{"issue_post":1},"nvrsbr":{"issue_post":1},"Aces-and-Jacks":{"issue_post":2},"caaaat1":{"issue_post":1,"issue_comment":2},"OskarSl66":{"issue_post":1},"ReflexArc1":{"issue_post":1},"sternschnaube":{"issue_post":1,"issue_comment":2},"Meawerful":{"issue_post":1,"issue_comment":1},"JadeHeartDeer":{"issue_post":1},"rheogus54":{"issue_post":1},"Zelioth":{"issue_post":1,"issue_comment":1},"akemin-dayo":{"issue_post":1,"issue_comment":2},"DanMeadWasTaken":{"issue_post":1},"Grumpey102":{"issue_post":1},"pewblaze":{"issue_post":1},"PaladinFallen":{"issue_post":1},"wiktorFIFLAK":{"issue_post":1},"cpm9":{"issue_post":1},"BlueberryYum":{"issue_post":1,"issue_comment":1},"Foxydapirate12":{"issue_post":1},"Seanniex":{"issue_post":1},"SplendidAlakey":{"issue_comment":3},"TechPro424":{"issue_comment":1},"TheFantasticLoki":{"issue_comment":1},"ksorah1":{"issue_comment":1},"acikek":{"issue_comment":1},"dadoirie":{"issue_comment":1},"santiphap-luml":{"issue_comment":1},"dagreenkat":{"issue_comment":1},"palindali":{"issue_comment":1},"Jolihan566":{"issue_comment":1},"KirboSoftware":{"issue_comment":1},"ygoroffici":{"issue_comment":1},"bipsydev":{"issue_comment":1},"Aninuscsalas":{"issue_comment":1},"Vinzound":{"issue_comment":1},"Zedrimar":{"issue_comment":2},"TLOM-Official":{"issue_comment":1},"St4rStr1ker":{"issue_comment":1},"Wanishekkk":{"issue_comment":2},"Morokor":{"issue_comment":1}}