{"DemonSeedxp":{"issue_post":1,"issue_comment":2},"Thunderrock424242":{"issue_post":1,"issue_comment":4},"TheGag96":{"issue_post":1,"issue_comment":1},"LostLuma":{"pr_post":1,"issue_post":1,"issue_comment":1},"RinixGG":{"pr_post":2,"issue_post":1,"issue_comment":1,"pr_comment":3},"StunfMC":{"issue_post":3,"issue_comment":1},"ghost":{"issue_post":2,"pr_post":2,"pr_comment":4,"issue_comment":2},"skibidibada":{"issue_post":1},"lostopkk":{"issue_post":1},"Devilswarchild":{"issue_post":1},"Zorklis":{"issue_post":2,"issue_comment":1},"Dekamir":{"issue_post":1,"issue_comment":1},"soupglasses":{"issue_post":1},"RDP8":{"issue_post":1,"issue_comment":3},"Candymanmax":{"issue_post":1,"issue_comment":1},"Felix14-v2":{"issue_post":1,"issue_comment":9,"pr_comment":3},"variety754":{"issue_post":1},"Andre601":{"issue_post":2,"issue_comment":1},"StockiesLad":{"pr_post":11,"issue_post":5,"issue_comment":219,"pr_comment":12},"LPDawid":{"issue_post":1,"issue_comment":1},"vico93":{"issue_post":1,"issue_comment":1},"MSandro":{"issue_post":1,"issue_comment":1},"sternschnaube":{"issue_post":1,"issue_comment":3},"Kaizodude":{"issue_post":1,"issue_comment":1},"ImGRUI":{"issue_post":1},"RaptaG":{"issue_post":1,"issue_comment":4},"Tema159":{"issue_post":1,"issue_comment":4},"TheBossMagnus":{"pr_post":1},"harithmf":{"issue_post":1},"notlin4":{"pr_post":1,"pr_comment":1},"maxguuse":{"issue_post":1},"NoltoxGit":{"issue_post":1},"itsdinkd":{"issue_post":1},"Kichura":{"issue_post":4,"issue_comment":7,"pr_comment":1},"Cape-City":{"issue_post":1,"issue_comment":2},"forditt":{"issue_post":1,"issue_comment":1},"Sogardd":{"issue_post":1,"issue_comment":1},"HyperSoop":{"issue_post":1,"issue_comment":2},"DreenDex":{"issue_post":1,"issue_comment":2},"HaXrBOT":{"issue_post":2},"Imzxhir":{"issue_post":1},"eatsomeapples":{"issue_post":1},"Atlantispy":{"issue_post":1},"SpiritOTHawk":{"issue_post":1},"NaiNonTH":{"issue_post":1},"KirboSoftware":{"pr_post":1,"issue_comment":10,"pr_comment":6},"GaucovyAero":{"issue_post":1},"Godeps2891":{"issue_post":1},"simcolin":{"issue_post":1},"bl205vn":{"pr_post":1},"MeeniMc":{"issue_post":1},"Cccc-owo":{"pr_post":1},"Proxwian":{"issue_post":1,"issue_comment":1},"FITFC":{"pr_post":1},"MinecraftFabricEnjoyer":{"issue_post":1},"Talbe1":{"issue_post":1,"issue_comment":8},"boasbakker":{"issue_post":1},"Lemmmy":{"issue_post":1,"issue_comment":1},"Kiryonn":{"issue_post":1,"issue_comment":1},"ChristopherHaws":{"issue_post":1,"issue_comment":1},"pokesmells":{"issue_post":1,"issue_comment":7},"KosmX":{"pr_post":1,"pr_comment":1},"KingContaria":{"pr_post":1},"MihailDenisov":{"issue_post":1},"InteJason":{"issue_post":1},"SugarDaddii":{"issue_post":1},"choombdev":{"issue_post":1},"Fnige":{"pr_post":1},"jinkhya":{"issue_post":1,"issue_comment":2},"linux-leo":{"issue_post":1},"Disguys":{"issue_post":1},"Nevrai":{"issue_post":1,"issue_comment":2},"DTRW919":{"issue_post":1},"ardissaps":{"issue_post":2},"MrJorman":{"issue_post":1,"issue_comment":7},"Steveplays28":{"issue_post":1,"issue_comment":1},"DeGamersSpelen":{"issue_post":1,"issue_comment":1},"tzmanish":{"issue_post":1},"Funtimes909":{"issue_post":1},"crest1993":{"issue_post":1,"issue_comment":1},"dog-biscuit64":{"issue_post":1,"issue_comment":1},"AbdElAziz333":{"issue_comment":1},"Foxydapirate12":{"issue_comment":3},"katubug":{"issue_comment":1},"otavio-silva":{"issue_comment":1},"samos667":{"issue_comment":1},"AVuTuVA":{"issue_comment":1},"cplir-c":{"issue_comment":1},"Panda-X2":{"issue_comment":1},"DankstoneMC":{"issue_comment":1},"ZsoltiHUB":{"issue_comment":1},"srnyx":{"issue_comment":1},"Tetsuyamin":{"issue_comment":1},"Poopooracoocoo":{"issue_comment":3},"Devc2":{"issue_comment":1},"CrazyWolf13":{"issue_comment":1},"AoSankaku":{"issue_comment":1},"RoonMoonlight":{"issue_comment":2},"MrBOOMberMAN":{"issue_comment":1},"Soriiaano07":{"issue_comment":2},"Mathimino3":{"issue_comment":1},"Diego13303":{"issue_comment":1},"icynstant":{"issue_comment":2},"papamaionise":{"issue_comment":1},"its3D56":{"issue_comment":1},"cobaltlol":{"issue_comment":1},"UltraBlackLinux":{"issue_comment":3},"PinexC":{"issue_comment":1},"MLMII":{"issue_comment":1},"HyperKiko":{"issue_comment":1},"GlitchTime":{"issue_comment":1},"Haberno":{"issue_comment":1},"AzuraNVM":{"issue_comment":1},"DeshiDesu":{"issue_comment":3},"justjustjustjust":{"issue_comment":1},"Pixel1011":{"issue_comment":1},"VOrlando520":{"issue_comment":1},"User4716":{"issue_comment":1}}