{"vukkax":{"issue_post":1},"maximogta":{"issue_post":1},"Ivan-Khar":{"issue_post":1},"ArkVeil":{"issue_post":2,"issue_comment":3},"peow":{"issue_post":1},"sisby-folk":{"pr_post":4},"ryleu":{"issue_post":1},"caniplzjustlogin4godsakesthistakesforev":{"issue_post":1},"BardinTheDwarf":{"pr_post":1},"kuba26038":{"issue_post":1},"kyragit":{"issue_post":1},"Aquaeyes":{"issue_post":1},"Jarva":{"pr_post":1},"celsiusqc":{"issue_post":2,"issue_comment":1},"Festnt":{"issue_post":1},"slushie0":{"issue_post":1},"mayonaka8478":{"pr_post":1},"Sunconure11":{"issue_post":1,"issue_comment":6},"SpongeGuy":{"issue_post":1,"issue_comment":1},"Blugori":{"issue_post":2},"thelegitdolt":{"pr_post":1,"issue_comment":1},"Parkanizor":{"issue_post":1},"nekomaster1000":{"issue_post":2},"ChuijkYahus":{"pr_post":1},"Darkhax":{"pr_post":1},"ryanhcode":{"pr_post":3},"yrsegal":{"issue_comment":2},"amoooooo":{"issue_comment":3},"SammySemicolon":{"issue_comment":5,"pr_comment":1},"Fummowo":{"issue_comment":1},"genesy":{"issue_comment":1},"Ch1216":{"issue_comment":1},"egshels":{"pr_comment":1,"issue_comment":1},"CodeGiver01":{"issue_comment":1},"Dovencio":{"issue_comment":1}}