{"Aznoq3":{"issue_post":1},"Reshy":{"issue_post":1,"issue_comment":3},"Apollounknowndev":{"issue_post":7,"pr_post":3,"issue_comment":144,"pr_comment":1},"Explosif3005":{"issue_post":1,"issue_comment":1},"abby-cadabra":{"issue_post":1,"issue_comment":1},"Sm982":{"issue_post":1},"Qzertje":{"issue_post":2},"Driestcombee":{"issue_post":1,"issue_comment":4},"IntM4rco":{"issue_post":1,"issue_comment":2},"unparted":{"issue_post":1,"issue_comment":3},"Beanthief":{"issue_post":1},"SlackinLackin":{"issue_post":1},"SleepyXS":{"issue_post":1},"Hati-":{"issue_post":1,"issue_comment":1},"Sunconure11":{"issue_post":1},"deadspidervenom":{"issue_post":2},"Rad586":{"issue_post":3,"pr_post":1,"issue_comment":3},"onecreq":{"issue_post":1},"JimBob-bb":{"issue_post":1,"issue_comment":3},"Endgineer":{"issue_post":1},"krjencik":{"issue_post":1},"NolanHewitt":{"issue_post":2,"issue_comment":5},"sbsosa":{"issue_post":1,"issue_comment":1},"blackshot":{"issue_post":1,"issue_comment":2},"ambientNexus":{"issue_post":1,"issue_comment":2},"ReallyJustColin":{"issue_post":1},"ADGParadox":{"issue_post":1,"issue_comment":1},"AncletYinglet":{"issue_post":1},"Masonono":{"issue_post":1,"issue_comment":2},"tillbaxmann":{"issue_post":1},"Eli6267":{"issue_post":1},"oRadiatorExtrem":{"issue_post":1},"hanweiyyds":{"issue_post":1},"BerrieBuffel":{"issue_post":1,"issue_comment":1},"rhongobongo":{"issue_post":1},"Minato245":{"issue_post":1},"Crankonator":{"issue_post":1},"SamMcClatchey":{"issue_post":1},"JianhuiDong9999":{"issue_post":1},"Shadowyjp":{"issue_post":1},"kimoVoid":{"issue_post":1},"SanguineWaters":{"issue_post":2,"issue_comment":3},"vlad1m":{"issue_post":1},"MageOfGaming":{"issue_post":1,"issue_comment":3},"Hakuyako":{"issue_post":1},"grugsy":{"issue_post":1,"issue_comment":5},"Krachboomman":{"issue_post":1,"issue_comment":1},"gxnda":{"issue_post":1},"GrandAlbert":{"issue_post":1},"Lordphiphi":{"issue_post":1},"AsheX1":{"issue_post":1,"issue_comment":1},"freeeezin":{"issue_post":1,"issue_comment":2},"gabuly":{"issue_post":1},"SuggestionMan":{"issue_post":1},"HugoIsNotACoder":{"issue_post":1},"SynSym":{"issue_post":1,"issue_comment":1},"HB-Stratos":{"pr_post":1},"jmote":{"issue_post":1},"marewey":{"issue_post":1,"issue_comment":2},"pancakeofsin":{"issue_post":1,"issue_comment":1},"KostromDan":{"issue_post":2,"issue_comment":1},"Ectopekk":{"issue_post":1},"lawrencedumarey":{"issue_post":1,"issue_comment":5},"PatTheWizard":{"issue_post":1},"nco2k":{"issue_post":1},"BiddinWar":{"issue_post":1,"issue_comment":1},"BurgerBob886":{"issue_post":1},"Bablela26":{"issue_post":1},"Boba194230":{"issue_post":1},"lunanium":{"issue_post":1,"issue_comment":1},"Y1rd":{"issue_post":1,"issue_comment":3},"hamer51":{"issue_post":1,"issue_comment":4},"Answordy":{"issue_post":2},"HerrBeef":{"issue_post":1},"stlouisn":{"pr_post":1},"Matthysse":{"issue_post":2},"ChunkyMonkey54":{"issue_post":2},"ConqAra":{"issue_post":1},"loftoxos":{"issue_post":1},"makumaku1974":{"issue_post":1},"VlRlON":{"issue_post":1},"Arasarhood":{"issue_post":1},"aNinjin":{"issue_post":1,"issue_comment":1},"ghost":{"issue_post":1},"Despaitre876":{"issue_post":1},"MadTheViking":{"issue_post":1},"TheRealIceCracker":{"issue_post":1,"issue_comment":1},"QuentinLeCaignec":{"issue_post":1,"issue_comment":1},"murao-kun":{"issue_post":1},"SamuelUlep":{"issue_post":1,"issue_comment":2},"Samapoke":{"issue_post":1,"issue_comment":1},"Thefatsparrow":{"issue_post":2,"issue_comment":2},"second2050":{"issue_post":1,"issue_comment":1},"ALPHAGAMER42":{"issue_post":1,"issue_comment":1},"cayenne-cep":{"issue_post":1,"issue_comment":2},"glorification12":{"issue_post":1},"ClaudioHidalgo03":{"issue_post":1},"arovium":{"issue_post":1},"MythrilBagels":{"issue_post":1,"issue_comment":1},"Ravn73":{"issue_post":1},"Rebel459":{"issue_post":2,"issue_comment":8},"J5ck5":{"issue_post":1},"saerdodus":{"issue_post":1,"issue_comment":1},"Coosanta17":{"issue_post":1},"vivagabe":{"issue_post":1},"emceeweeb":{"issue_post":1},"wjzczzjl2020":{"issue_post":1},"An-thracene":{"issue_post":1},"b0b4444":{"issue_post":1},"kunieone":{"issue_post":1},"alcatrazEscapee":{"issue_post":1},"Menlor":{"issue_post":1},"bit-paper":{"issue_post":1},"Aces-and-Jacks":{"issue_post":2,"issue_comment":9},"SpudGunMcGee":{"issue_comment":4},"LunarPidgeon":{"issue_comment":1},"Jaximo98-dev":{"issue_comment":2},"ChoiceTheorem":{"issue_comment":1},"ChosenMoren":{"issue_comment":1},"DavidBlackCN":{"issue_comment":1},"DeadRedmond":{"issue_comment":2},"HollowedWanderer":{"issue_comment":2},"SaltSouls":{"issue_comment":2},"CtrldChaos101":{"issue_comment":1},"IDonutKnowYT":{"issue_comment":1},"fightmesun":{"issue_comment":1},"thelyric27":{"issue_comment":2},"Edrow-6":{"issue_comment":1},"CODwar2005":{"issue_comment":1},"virtualsaturn":{"issue_comment":1},"highlunlikely":{"issue_comment":1},"BarteG44":{"issue_comment":1},"zoqin":{"issue_comment":1},"ionutsoran":{"issue_comment":1},"Mecheon":{"issue_comment":1},"Kyles1201":{"issue_comment":2},"ghosty141":{"issue_comment":2},"Otateriheem":{"issue_comment":1},"RN0000":{"issue_comment":1},"mccalltristan":{"issue_comment":1},"Villanueva-Flavio":{"issue_comment":1},"samuelbarrett":{"issue_comment":1},"m3t4f1v3":{"issue_comment":3},"AlarkiusJay":{"issue_comment":1},"NanoGalacticHasNeverBeenTakenBeforewtf":{"issue_comment":1},"taitep":{"issue_comment":1}}