{"Kreygasm13":{"issue_post":1,"issue_comment":1},"xR4YM0ND":{"pr_post":1},"joernott":{"issue_post":1,"issue_comment":2},"netcore10":{"issue_post":1,"issue_comment":1},"seilkomet64":{"issue_post":1},"dhouck":{"issue_post":1},"Chris6ix":{"issue_post":1},"hugoueng01":{"issue_post":1},"GreeceGuy":{"issue_post":1},"koiboi-dev":{"issue_post":1},"OctavioCore":{"issue_post":1},"Dreamer-40":{"pr_post":2},"dryas-octopetala":{"issue_post":1},"AngryTurtlex":{"issue_post":1},"leonardig08":{"issue_post":1,"issue_comment":1},"pikminman13":{"issue_post":1,"issue_comment":1},"Saereth":{"issue_post":1,"issue_comment":5},"ConqAra":{"issue_post":1},"MehVahdJukaar":{"issue_post":1},"getItemFromBlock":{"issue_post":1,"issue_comment":1},"ghost":{"issue_post":1,"issue_comment":2},"NuoranDFDG":{"issue_post":1},"Leelin1":{"issue_post":1},"SGZ-Creations":{"issue_post":1,"issue_comment":1},"steve-the-player":{"issue_post":2,"issue_comment":1},"lonevox":{"issue_post":1},"DaPuffer":{"issue_post":1,"issue_comment":7},"crazytwelve":{"issue_post":1},"JonasFranke":{"pr_post":1},"Merloss":{"pr_post":1},"1luik":{"issue_post":1},"NeroWT":{"issue_post":1,"issue_comment":2},"emmod-190":{"issue_post":1,"issue_comment":1},"Nycto97":{"issue_post":2,"issue_comment":8},"Yarden-zamir":{"pr_post":1,"issue_post":1,"issue_comment":11},"gamma-delta":{"issue_post":1},"ChiefEhoy19":{"issue_post":1,"issue_comment":4},"MajerIV":{"pr_post":1},"Cynical1115":{"issue_post":1,"issue_comment":2},"YaogouYuki":{"issue_post":1,"issue_comment":1},"V3rt3x824":{"issue_post":1,"issue_comment":1},"burdoto":{"issue_post":1,"issue_comment":1},"Qian-F":{"issue_post":1,"issue_comment":12},"Hardziplay":{"pr_post":3,"pr_comment":2},"Catchmons":{"pr_post":1},"c0gd1s":{"issue_post":1,"issue_comment":1},"u7f8au7fbd":{"pr_post":2,"issue_post":1},"ziad25139":{"issue_post":1,"issue_comment":1},"qwek1":{"issue_post":1,"issue_comment":1},"VGamerGroup":{"pr_post":2,"pr_comment":5},"CamKablam":{"issue_post":1},"Vilcu-Valentin":{"issue_post":1},"mortuusars":{"issue_post":2},"c0d3-404":{"issue_post":1},"Devilswarchild":{"issue_post":2,"issue_comment":1},"Obfus-8":{"issue_post":1},"lysolaka":{"pr_post":1},"Gensokian":{"issue_post":1,"issue_comment":1},"Nanevo":{"issue_post":1,"issue_comment":2},"T34256":{"issue_post":1,"issue_comment":2},"vizthex123":{"issue_post":1,"issue_comment":1},"billjk2013":{"issue_post":1,"issue_comment":1},"Thefuzz1234555":{"pr_post":1},"lays24mc":{"issue_post":1,"issue_comment":1},"Ronzaigu":{"pr_post":1,"pr_comment":1},"Allerek":{"issue_post":1},"SuddenlySentient":{"issue_post":1},"Xyphenore":{"issue_post":2,"issue_comment":1},"Zakimon502":{"issue_post":1},"AsseyGithub":{"pr_post":1},"MythrilBagels":{"issue_post":1},"celsiusqc":{"issue_post":2},"CathieNova":{"issue_post":1,"issue_comment":1},"MindFaer":{"issue_post":1},"poly-1810":{"issue_post":1},"garrowson":{"issue_post":1},"george8188625":{"issue_comment":80,"pr_comment":4},"MrNavaStar":{"issue_comment":1},"PikachuGabe":{"issue_comment":1},"ProTerUga":{"pr_comment":1},"FoxyFox909":{"issue_comment":1},"cout970":{"issue_comment":1},"NaveNosliv":{"issue_comment":1},"gmhs022":{"issue_comment":2},"TheBlckbird":{"issue_comment":1},"HTony03":{"issue_comment":1},"DatenThielt":{"issue_comment":2},"sherlockzym":{"issue_comment":2},"JulanDeAlb":{"issue_comment":1},"Tursiops-G":{"issue_comment":1},"GustavJones":{"issue_comment":1},"Luke1505":{"issue_comment":1},"hatkidchan":{"issue_comment":4},"Trex11111":{"issue_comment":1}}