{"mpiId":7757,"id":237333,"name":"Futurepack Mod - Now with flyable Spaceships!","slug":"futurepack","sourceLink":"https://github.com/mcenderdragon/Futurepack-API","categories":["world-ores-resources","cosmetic","technology","world-dimensions","technology-item-fluid-energy-transport"],"devs":["mcenderdragon"],"dependencies":{"69118":2,"74072":2,"223794":2,"229060":2,"238222":2,"239197":2,"267602":2,"275300":2,"282001":2,"297039":2,"309927":2,"353928":2,"361276":2},"summary":"The Futurepack is a modification adding future-themed materials, resources and other stuff.","logoUrl":"https://media.forgecdn.net/avatars/27/633/635813646545673380.png","downloadCount":1157983}