{"mpiId":33119,"id":575513,"name":"Fantasy Origins [Fabric]","slug":"fantasy-origins-fabric","sourceLink":"https://github.com/NickSuttonDicken/FantasyOrigins","categories":["world-mobs","armor-weapons-tools","adventure-rpg"],"devs":["froztigaming"],"dependencies":{"318440":2,"319596":3,"348521":3,"391943":3,"398419":3},"summary":"A Fabric Minecraft Mod that adds Blocks, Mobs, Items, and Origins","logoUrl":"https://media.forgecdn.net/avatars/488/773/637793776989225353.png","downloadCount":156335}