{"mpiId":2930,"id":59648,"name":"Kitteh6660's MoreCraft","slug":"kitteh6660s-morecraft","sourceLink":"https://github.com/Kitteh6660/MoreCraft","categories":["armor-weapons-tools","adventure-rpg","world-ores-resources","mc-food"],"devs":["kitteh6660"],"dependencies":{"227639":2,"243121":2,"380617":2,"382216":2,"398521":2,"430988":2,"543610":2},"summary":"Enhance your vanilla experience with a large yet simple Forge mod that adds over 100 items and several new blocks.","logoUrl":"https://media.forgecdn.net/avatars/470/512/637757521542557138.png","downloadCount":153602}