{"mpiId":35136,"id":609886,"name":"PackagedMekemicals","slug":"packagedmekemicals","sourceLink":"https://github.com/TheLMiffy1111/PackagedMekemicals","categories":["applied-energistics-2","mc-addons","technology-automation","technology-item-fluid-energy-transport"],"devs":["thelmiffy1111"],"dependencies":{"223794":2,"268560":3,"308380":3,"574300":2},"summary":"Use Mekanism Chemicals in PackagedAuto","logoUrl":"https://media.forgecdn.net/avatars/537/908/637862300757190817.png","downloadCount":41664}