{"mpiId":46440,"id":899487,"name":"Better chunk loading[Forge/Fabric]","slug":"better-chunk-loading-forge-fabric","sourceLink":"https://github.com/someaddons/betterchunkloading","categories":["adventure-rpg","server-utility","map-information","utility-qol","world-biomes"],"devs":["someaddon"],"dependencies":{"326652":3},"summary":"Predicts player movement to pre-load chunks and increases chunk load speed","logoUrl":"https://media.forgecdn.net/avatars/861/519/638269254479355298.png","downloadCount":6806966}