{"mpiId":52500,"id":927591,"name":"Fright's Delight [Fabric]","slug":"frights-delight","sourceLink":"https://github.com/ChefMooon/frights-delight","categories":["mc-addons","mc-food","cosmetic"],"devs":["chefmooon"],"dependencies":{"306612":3,"482834":3,"993166":3},"summary":"Fright’s Delight is an add-on mod for Farmer’s Delight Fabric that adds food made from mob drops. Dishes are created with a “Horror” theme, consume with caution. ","logoUrl":"https://media.forgecdn.net/avatars/894/741/638338713542912163.png","downloadCount":135087}